sentimeter/__init__.py
sentimeter/backend.py
sentimeter/chatgpt_backend.py
sentimeter/engine_observer.py
sentimeter/file_audio_source.py
sentimeter/live_speech_source.py
sentimeter/local_backend.py
sentimeter/sentimeter.py
sentimeter/sources.py
sentimeter/speech_to_text.py
sentimeter-0.0.5.dist-info/WHEEL
sentimeter-0.0.5.dist-info/METADATA
sentimeter-0.0.5.dist-info/RECORD
